{
	"info": {
		"_postman_id": "05699c25-5366-47eb-94f4-edb128c12e07",
		"name": "Generated Collection from Definition",
		"schema": "https://schema.getpostman.com/json/collection/v2.1.0/collection.json",
		"_uid": "889210-05699c25-5366-47eb-94f4-edb128c12e07"
	},
	"item": [
		{
			"name": "Sample endpoint: Returns details about",
			"id": "bf23b190-fa88-41c5-a7ba-e0776f0e411f",
			"protocolProfileBehavior": {
				"disableBodyPruning": true
			},
			"request": {
				"method": "GET",
				"header": [
					{
						"key": "Accept",
						"value": "application/json"
					}
				],
				"url": {
					"raw": "{{baseUrl}}/user?id=8533570",
					"host": [
						"{{baseUrl}}"
					],
					"path": [
						"user"
					],
					"query": [
						{
							"key": "id",
							"value": "8533570",
							"description": "(Required) ID of the user"
						}
					]
				}
			},
			"response": [
				{
					"id": "67157082-7ccc-42e0-96a6-8e7aee68fd42",
					"name": "Sample response: Details about a user by ID",
					"originalRequest": {
						"method": "GET",
						"header": [],
						"url": {
							"raw": "{{baseUrl}}/user?id=8533570",
							"host": [
								"{{baseUrl}}"
							],
							"path": [
								"user"
							],
							"query": [
								{
									"key": "id",
									"value": "8533570"
								}
							]
						}
					},
					"status": "OK",
					"code": 200,
					"_postman_previewlanguage": "json",
					"header": [
						{
							"disabled": false,
							"description": "A link to the next page of responses",
							"key": "x-next",
							"value": "deserunt"
						},
						{
							"key": "Content-Type",
							"value": "application/json"
						}
					],
					"cookie": [],
					"body": "{\n  \"id\": 68966661,\n  \"name\": \"minim cupidatat sit\",\n  \"tag\": \"minim deserunt nostrud\"\n}"
				},
				{
					"id": "227a0e26-c13d-4eb6-93cc-85a737146d8c",
					"name": "Unexpected error has just occurred",
					"originalRequest": {
						"method": "GET",
						"header": [],
						"url": {
							"raw": "{{baseUrl}}/user?id=8533570",
							"host": [
								"{{baseUrl}}"
							],
							"path": [
								"user"
							],
							"query": [
								{
									"key": "id",
									"value": "8533570"
								}
							]
						}
					},
					"status": "Internal Server Error",
					"code": 500,
					"_postman_previewlanguage": "json",
					"header": [
						{
							"key": "Content-Type",
							"value": "application/json"
						}
					],
					"cookie": [],
					"body": "{\n  \"code\": -58603557,\n  \"message\": \"ven\"\n}"
				}
			]
		},
		{
			"name": "Sample endpoin",
			"id": "bc3ea611-3edf-47e2-866a-132e5644e968",
			"protocolProfileBehavior": {
				"disableBodyPruning": true
			},
			"request": {
				"method": "GET",
				"header": [
					{
						"key": "Accept",
						"value": "application/json"
					}
				],
				"url": {
					"raw": "{{baseUrl}}/user?id=8533570",
					"host": [
						"{{baseUrl}}"
					],
					"path": [
						"user"
					],
					"query": [
						{
							"key": "id",
							"value": "8533570",
							"description": "(Required) ID of the user"
						}
					]
				}
			},
			"response": [
				{
					"id": "6bafe3db-49cd-46a6-9821-fd44aaf4f5f6",
					"name": "Sample response: Details about a user by ID",
					"originalRequest": {
						"method": "GET",
						"header": [],
						"url": {
							"raw": "{{baseUrl}}/user?id=8533570",
							"host": [
								"{{baseUrl}}"
							],
							"path": [
								"user"
							],
							"query": [
								{
									"key": "id",
									"value": "8533570"
								}
							]
						}
					},
					"status": "OK",
					"code": 200,
					"_postman_previewlanguage": "json",
					"header": [
						{
							"disabled": false,
							"description": "A link to the next page of responses",
							"key": "x-next",
							"value": "deserunt"
						},
						{
							"key": "Content-Type",
							"value": "application/json"
						}
					],
					"cookie": [],
					"body": "{\n  \"id\": 68966661,\n  \"name\": \"minim cupidatat sit\",\n  \"tag\": \"minim deserunt nostrud\"\n}"
				},
				{
					"id": "6d97cea4-d7f6-4a01-8ec6-9fb9f855ddb7",
					"name": "Unexpected error has just occurred",
					"originalRequest": {
						"method": "GET",
						"header": [],
						"url": {
							"raw": "{{baseUrl}}/user?id=8533570",
							"host": [
								"{{baseUrl}}"
							],
							"path": [
								"user"
							],
							"query": [
								{
									"key": "id",
									"value": "8533570"
								}
							]
						}
					},
					"status": "Internal Server Error",
					"code": 500,
					"_postman_previewlanguage": "json",
					"header": [
						{
							"key": "Content-Type",
							"value": "application/json"
						}
					],
					"cookie": [],
					"body": "{\n  \"code\": -58603557,\n  \"message\": \"ven\"\n}"
				}
			]
		}
	],
	"variable": [
		{
			"id": "5aafac7e-94d1-46d7-a062-45366d244a91",
			"key": "baseUrl",
			"value": "http://localhost:3000",
			"type": "string"
		}
	]
}